django/singlefile/__init__.py
django/singlefile/environment.py
django_singlefile-0.2.2.dist-info/METADATA
django_singlefile-0.2.2.dist-info/WHEEL
django_singlefile-0.2.2.dist-info/top_level.txt
django_singlefile-0.2.2.dist-info/RECORD
