Metadata-Version: 2.1
Name: django-singlefile
Version: 0.2.2
Summary: A library to make single-file Django apps easier
Author-email: Andrew Godwin <andrew@aeracode.org>
License: BSD-3-Clause
Project-URL: Homepage, https://github.com/andrewgodwin/django-singlefile
Classifier: Framework :: Django
Classifier: Programming Language :: Python :: 3
Requires-Python: >=3.10
Requires-Dist: Django >=5
Requires-Dist: whitenoise ~=6.6.0
